LICENSE
README.md
setup.py
vial/__init__.py
vial/loginmanager.py
vial/request.py
vial/response.py
vial/route.py
vial/utils.py
vial_http.egg-info/PKG-INFO
vial_http.egg-info/SOURCES.txt
vial_http.egg-info/dependency_links.txt
vial_http.egg-info/top_level.txt