Metadata-Version: 2.1
Name: vial-http
Version: 0.3.4
Summary: WSGI based HTTP nano-framework
Home-page: https://github.com/martastain/vial
Author: Martin Wacker
Author-email: martas@imm.cz
License: MIT
Keywords: http server minimal wsgi api
Platform: UNKNOWN
Classifier: Development Status :: 3 - Alpha
Classifier: Environment :: Console
Classifier: Intended Audience :: Developers
Classifier: License :: OSI Approved :: MIT License
Classifier: Natural Language :: English
Classifier: Operating System :: POSIX :: Linux
Classifier: Programming Language :: Python
Classifier: Topic :: Internet :: WWW/HTTP :: HTTP Servers
Classifier: Topic :: Internet :: WWW/HTTP :: WSGI :: Server
License-File: LICENSE
